{
  "name": "corrosive-ui",
  "path": "./src",
  "setup_dependency": {
    "dependents": {
      "Task(setup_ui_pass)": [
        "Task(run_renderer)"
      ],
      "Task(run_renderer)": []
    },
    "in_degrees": {
      "Task(run_renderer)": 1,
      "Task(setup_ui_pass)": 0
    }
  },
  "runtime_dependency": {
    "dependents": {
      "Task(rerender_ui)": []
    },
    "in_degrees": {
      "Task(rerender_ui)": 0
    }
  },
  "sync_dependency": {
    "dependents": {},
    "in_degrees": {}
  },
  "tasks": {
    "rerender_ui": [
      "Update",
      null
    ],
    "setup_ui_pass": [
      "Setup",
      null
    ]
  },
  "packages": []
}